diffgeom/__init__.py
diffgeom/diffgeom.py
diffgeom-0.0.1.dist-info/METADATA
diffgeom-0.0.1.dist-info/WHEEL
diffgeom-0.0.1.dist-info/top_level.txt
diffgeom-0.0.1.dist-info/RECORD
